jhsp/__init__.py
jhsp/test.py
jhsp/ClassTools/__init__.py
jhsp/ClassTools/collatingwords.py
jhsp/ClassTools/sound.py
jhsp/Data/__init__.py
jhsp/Data/GetXY/__init__.py
jhsp/Data/GetXY/get_xy.py
jhsp/Data/Preprocessing/__init__.py
jhsp/Data/Preprocessing/codingdata.py
jhsp/Data/Preprocessing/describingdata.py
jhsp/Data/Preprocessing/selectingfeatures.py
jhsp/Data/Standardization/__init__.py
jhsp/Data/Standardization/standardization.py
jhsp/Decorators/IsolatingParameters.py
jhsp/Decorators/__init__.py
jhsp/FunTools/Add_top_path.py
jhsp/FunTools/__init__.py
jhsp/FunTools/load_config.py
jhsp/FunTools/multi_process.py
jhsp/FunTools/my_pow.py
jhsp/FunTools/my_split.py
jhsp/FunTools/my_split_list.py
jhsp/Model/__init__.py
jhsp/Model/trad_models_parameters.py
jhsp/Model/Compare/__init__.py
jhsp/Model/Compare/get_model_score.py
jhsp/Model/Optimize/__init__.py
jhsp/Model/Optimize/default_config.py
jhsp/Model/Optimize/get_best_model.py
jhsp/Sann/__init__.py
jhsp/Sann/get_model.py
jhsp/Sann/getweights.py
jhsp/Sann/weights22netweights.py
jhsp/Sann/models/__init__.py
jhsp/Sann/models/anntuner.py
jhsp/Sann/models/sann.py
jhsp/Sann/models/sanntuner.py
jhsp/TorchPipeline/__init__.py
jhsp/TorchPipeline/config_torchpipeline.py
jhsp-0.0.55.dist-info/LICENSE
jhsp-0.0.55.dist-info/METADATA
jhsp-0.0.55.dist-info/WHEEL
jhsp-0.0.55.dist-info/top_level.txt
jhsp-0.0.55.dist-info/RECORD
