Metadata-Version: 2.1
Name: jhsp
Version: 0.0.55
Summary: A package only used by Junhe Zhao
Home-page: https://pypi.org
Author: Junhe Zhao
Author-email: zhaozong111@gmail.com
License: UNKNOWN
Platform: UNKNOWN
